devi/__init__.py
devi/__main__.py
devi/config.py
devi/toml_parser.py
devi/utils.py
devi/cli/__init__.py
devi/cli/args_parser.py
devi/cli/log.py
devi/cli/main.py
devi/commands/add_template.py
devi/commands/create.py
devi/commands/list.py
devi/commands/remove.py
devi_cli-0.2.1.dist-info/LICENSE
devi_cli-0.2.1.dist-info/METADATA
devi_cli-0.2.1.dist-info/WHEEL
devi_cli-0.2.1.dist-info/entry_points.txt
devi_cli-0.2.1.dist-info/top_level.txt
devi_cli-0.2.1.dist-info/RECORD
