Metadata-Version: 2.1
Name: devi-cli
Version: 0.2.1
Summary: devi is a cli tool for managing your project templates
Author-email: Paolo Flores <paolo.flores2@unmsm.edu.pe>
Project-URL: repository, https://github.com/paoloose/devi
Project-URL: issues, https://github.com/paoloose/devi/issues
Keywords: templates,project,cli tool,organization,productivity
Classifier: Programming Language :: Python :: 3
Classifier: License :: OSI Approved :: MIT License
Classifier: Operating System :: OS Independent
Requires-Python: >=3.7
License-File: LICENSE
Requires-Dist: docopt
Requires-Dist: tomli ; python_version < "3.11"
